{"description":"should navigate to GOM production summary page and validate if all the components are displayed|Production Summary Test","passed":true,"pending":false,"os":"Windows NT","instanceId":1128,"browser":{"name":"chrome","version":"70.0.3538.77"},"message":"Passed.","trace":"","browserLogs":[{"level":"SEVERE","message":"http://webuidev/ipso/common/config.json - Failed to load resource: the server responded with a status of 404 (Not Found)","timestamp":1542107455273,"type":""},{"level":"WARNING","message":"http://webuidev/ipso/main.02e06814a3144a4967bb.js 0:1568194 \"Deprecation warning: moment().subtract(period, number) is deprecated. Please use moment().subtract(number, period). See http://momentjs.com/guides/#/warnings/add-inverted-param/ for more info.\"","timestamp":1542107467484,"type":""}],"screenShotFile":"00680027-009d-00df-00c4-00dd0086006e.png","timestamp":1542107453297,"duration":15524}
